sou_meraki/__init__.py
sou_meraki/controller.py
sou_meraki/misc.py
sou_meraki/model.py
sou_meraki/view.py
sou_meraki/input/__init__.py
sou_meraki/input/settings.toml
sou_meraki/output/logs/.gitignore
sou_meraki-0.0.3.dist-info/LICENSE
sou_meraki-0.0.3.dist-info/METADATA
sou_meraki-0.0.3.dist-info/WHEEL
sou_meraki-0.0.3.dist-info/entry_points.txt
sou_meraki-0.0.3.dist-info/top_level.txt
sou_meraki-0.0.3.dist-info/RECORD
