Metadata-Version: 2.1
Name: sou-meraki
Version: 0.0.3
License-File: LICENSE
Requires-Dist: aiohttp (==3.8.4)
Requires-Dist: aiosignal (==1.3.1)
Requires-Dist: async-timeout (==4.0.2)
Requires-Dist: attrs (==23.1.0)
Requires-Dist: certifi (==2023.5.7)
Requires-Dist: charset-normalizer (==3.1.0)
Requires-Dist: frozenlist (==1.3.3)
Requires-Dist: idna (==3.4)
Requires-Dist: meraki (==1.34.0)
Requires-Dist: multidict (==6.0.4)
Requires-Dist: requests (==2.31.0)
Requires-Dist: tomlkit (==0.11.8)
Requires-Dist: urllib3 (==2.0.3)
Requires-Dist: yarl (==1.9.2)
